{"trial_id": "00", "hyperparameters": {"space": [{"class_name": "Int", "config": {"name": "dense_units", "default": null, "conditions": [], "min_value": 32, "max_value": 256, "step": 32, "sampling": "linear"}}, {"class_name": "Choice", "config": {"name": "learning_rate", "default": 0.01, "conditions": [], "values": [0.01, 0.001, 0.0001], "ordered": true}}], "values": {"dense_units": 192, "learning_rate": 0.0001}}, "metrics": {"metrics": {"loss": {"direction": "min", "observations": [{"value": [0.9266578555107117], "step": 4}]}, "accuracy": {"direction": "max", "observations": [{"value": [0.5236188769340515], "step": 4}]}, "val_loss": {"direction": "min", "observations": [{"value": [0.9558693170547485], "step": 4}]}, "val_accuracy": {"direction": "max", "observations": [{"value": [0.5343999862670898], "step": 4}]}}}, "score": 0.5343999862670898, "best_step": 4, "status": "COMPLETED", "message": null}